functions_by_aselya2507/README.md
functions_by_aselya2507/math_functions.py
functions_by_aselya2507-0.2.0.dist-info/WHEEL
functions_by_aselya2507-0.2.0.dist-info/METADATA
functions_by_aselya2507-0.2.0.dist-info/RECORD
