Metadata-Version: 2.1
Name: functions-by-aselya2507
Version: 0.2.0
Summary: this is our test project
Author: Assel Agaidarova
Author-email: aselya25789@gmail.com
Requires-Python: >=3.10,<4.0
Classifier: Programming Language :: Python :: 3
Classifier: Programming Language :: Python :: 3.10
Classifier: Programming Language :: Python :: 3.11
